fusion_platform/__init__.py
fusion_platform/__main__.py
fusion_platform/base.py
fusion_platform/command.py
fusion_platform/detailed_example.py
fusion_platform/documentation.py
fusion_platform/fusion_platform_sdk.pdf
fusion_platform/glasgow.geojson
fusion_platform/lake_district.geojson
fusion_platform/localisations.py
fusion_platform/localise.py
fusion_platform/quick_example.py
fusion_platform/session.py
fusion_platform/translations.py
fusion_platform/common/__init__.py
fusion_platform/common/raise_thread.py
fusion_platform/common/utilities.py
fusion_platform/models/__init__.py
fusion_platform/models/credit.md
fusion_platform/models/credit.py
fusion_platform/models/data.md
fusion_platform/models/data.py
fusion_platform/models/data_file.md
fusion_platform/models/data_file.py
fusion_platform/models/fields.py
fusion_platform/models/model.py
fusion_platform/models/organisation.md
fusion_platform/models/organisation.py
fusion_platform/models/process.md
fusion_platform/models/process.py
fusion_platform/models/process_execution.md
fusion_platform/models/process_execution.py
fusion_platform/models/process_service_execution.md
fusion_platform/models/process_service_execution.py
fusion_platform/models/process_service_execution_log.md
fusion_platform/models/process_service_execution_log.py
fusion_platform/models/service.md
fusion_platform/models/service.py
fusion_platform/models/user.md
fusion_platform/models/user.py
fusion_platform_python_sdk-2.1.1.dist-info/licenses/LICENSE.txt
fusion_platform_python_sdk-2.1.1.dist-info/METADATA
fusion_platform_python_sdk-2.1.1.dist-info/WHEEL
fusion_platform_python_sdk-2.1.1.dist-info/entry_points.txt
fusion_platform_python_sdk-2.1.1.dist-info/top_level.txt
fusion_platform_python_sdk-2.1.1.dist-info/RECORD
