Metadata-Version: 2.4
Name: fusion-platform-python-sdk
Version: 2.1.1
Summary: Python SDK used to interact with the Fusion Platform(r)
Home-page: https://github.com/d-cat-support/fusion-platform-python-sdk
Author: Digital Content Analysis Technology Ltd
Author-email: support@d-cat.co.uk
License: MIT
Classifier: Programming Language :: Python :: 3
Classifier: Programming Language :: Python :: 3.9
Classifier: Programming Language :: Python :: 3.10
Classifier: Programming Language :: Python :: 3.11
Classifier: Programming Language :: Python :: 3.12
Classifier: Programming Language :: Python :: 3.13
License-File: LICENSE.txt
Requires-Dist: marshmallow
Requires-Dist: pathos
Requires-Dist: prompt_toolkit
Requires-Dist: pyjwt
Requires-Dist: python-dateutil
Requires-Dist: python-i18n[YAML]
Requires-Dist: requests
Requires-Dist: tenacity
Requires-Dist: tqdm
Dynamic: author
Dynamic: author-email
Dynamic: classifier
Dynamic: description
Dynamic: description-content-type
Dynamic: home-page
Dynamic: license
Dynamic: license-file
Dynamic: requires-dist
Dynamic: summary
